pymedphys_fileformats/__init__.py
pymedphys_fileformats/_install_requires.py
pymedphys_fileformats/_version.py
pymedphys_fileformats/delivery/__init__.py
pymedphys_fileformats/delivery/core.py
pymedphys_fileformats/mapcheck/__init__.py
pymedphys_fileformats/mapcheck/core.py
pymedphys_fileformats/mephysto/__init__.py
pymedphys_fileformats/mephysto/api.py
pymedphys_fileformats/mephysto/core.py
pymedphys_fileformats/mephysto/mcc2csv.py
pymedphys_fileformats/profiler/__init__.py
pymedphys_fileformats/profiler/core.py
pymedphys_fileformats/trf/__init__.py
pymedphys_fileformats/trf/config.json
pymedphys_fileformats/trf/constants.py
pymedphys_fileformats/trf/header.py
pymedphys_fileformats/trf/table.py
pymedphys_fileformats/trf/trf2csv.py
pymedphys_fileformats/trf/trf2pandas.py
pymedphys_fileformats-0.11.0.dist-info/LICENSE-AGPL-3.0-or-later
pymedphys_fileformats-0.11.0.dist-info/LICENSE-Apache-2.0
pymedphys_fileformats-0.11.0.dist-info/METADATA
pymedphys_fileformats-0.11.0.dist-info/WHEEL
pymedphys_fileformats-0.11.0.dist-info/top_level.txt
pymedphys_fileformats-0.11.0.dist-info/RECORD
